marvel_func/__init__.py
marvel_func/api_call.py
marvel_func/char_filter.py
marvel_func-0.1.dist-info/LICENSE
marvel_func-0.1.dist-info/METADATA
marvel_func-0.1.dist-info/WHEEL
marvel_func-0.1.dist-info/top_level.txt
marvel_func-0.1.dist-info/RECORD
