Metadata-Version: 2.1
Name: marvel-func
Version: 0.1
Summary: Testing installation of Package
Home-page: UNKNOWN
Author: Starcst
License: MIT
Platform: UNKNOWN
License-File: LICENSE
